yapp/__init__.py
yapp/_version.py
yapp/adapters/__init__.py
yapp/adapters/file.py
yapp/adapters/pandas.py
yapp/adapters/pgsql.py
yapp/adapters/snowflake.py
yapp/adapters/sql.py
yapp/adapters/utils.py
yapp/cli/__init__.py
yapp/cli/logs.py
yapp/cli/parsing.py
yapp/cli/validation.py
yapp/core/__init__.py
yapp/core/attr_dict.py
yapp/core/errors.py
yapp/core/input_adapter.py
yapp/core/inputs.py
yapp/core/job.py
yapp/core/monitor.py
yapp/core/output_adapter.py
yapp/core/pipeline.py
yapp_pipelines-0.5.0.dist-info/LICENSE
yapp_pipelines-0.5.0.dist-info/METADATA
yapp_pipelines-0.5.0.dist-info/WHEEL
yapp_pipelines-0.5.0.dist-info/entry_points.txt
yapp_pipelines-0.5.0.dist-info/top_level.txt
yapp_pipelines-0.5.0.dist-info/RECORD
