Metadata-Version: 2.1
Name: yapp-pipelines
Version: 0.5.0
Summary: Yet Another Python (data) Pipeline
Home-page: https://github.com/cavenditti/yapp
Author: Carlo Antonio Venditti
Author-email: author@example.com
Project-URL: Bug Tracker, https://github.com/cavenditti/yapp/issues
Classifier: Programming Language :: Python :: 3
Classifier: License :: OSI Approved :: MIT License
Classifier: Operating System :: OS Independent
Requires-Python: >=3.9
License-File: LICENSE
Requires-Dist: pyyaml
Requires-Dist: cerberus
Requires-Dist: pandas
Requires-Dist: sqlalchemy
Requires-Dist: psycopg2
Requires-Dist: snowflake-connector-python
